radix_engine_toolkit/__init__.py
radix_engine_toolkit/__init__.pyi
radix_engine_toolkit/aarch64-apple-darwin
radix_engine_toolkit/aarch64-unknown-linux-gnu
radix_engine_toolkit/x86_64-apple-darwin
radix_engine_toolkit/x86_64-pc-windows-gnu.dll
radix_engine_toolkit/x86_64-unknown-linux-gnu
radix_engine_toolkit-2.3.2.dist-info/METADATA
radix_engine_toolkit-2.3.2.dist-info/WHEEL
radix_engine_toolkit-2.3.2.dist-info/top_level.txt
radix_engine_toolkit-2.3.2.dist-info/RECORD
